LICENSE
MANIFEST.in
README.rst
ledgrid.py
setup.cfg
setup.py
ledgrid.egg-info/PKG-INFO
ledgrid.egg-info/SOURCES.txt
ledgrid.egg-info/dependency_links.txt
ledgrid.egg-info/requires.txt
ledgrid.egg-info/top_level.txt