Metadata-Version: 1.1
Name: ledgrid
Version: 0.4
Summary: An 8x8 grid of virtual LEDs implemented in Pygame.
Home-page: https://github.com/zeth/ledgrid
Author: Zeth
Author-email: theology@gmail.com
License: BSD
Platform: UNKNOWN
Classifier: Programming Language :: Python :: 2.7
Classifier: Programming Language :: Python :: 3
Classifier: Intended Audience :: Developers
Classifier: License :: OSI Approved :: BSD License
Classifier: Topic :: Software Development :: Libraries
Classifier: Topic :: Utilities
